zcms
