Metadata-Version: 1.1
Name: zcms
Version: 0.5.7
Summary: Serve filesystem content via repoze.bfg
Home-page: http://zopen.cn
Author: Agendaless Consulting
Author-email: zhengping@zopen.cn
License: BSD-derived (http://www.repoze.org/LICENSE.txt)
Keywords: file server wsgi zope
Platform: UNKNOWN
Classifier: Development Status :: 4 - Beta
Classifier: Intended Audience :: Developers
Classifier: Programming Language :: Python
Classifier: Topic :: Internet :: WWW/HTTP
Classifier: Topic :: Internet :: WWW/HTTP :: Dynamic Content
Classifier: Topic :: Internet :: WWW/HTTP :: WSGI
Classifier: Topic :: Internet :: WWW/HTTP :: WSGI :: Application
